nspektr/__init__.py
nspektr/_compat.py
nspektr-0.5.1.dist-info/LICENSE
nspektr-0.5.1.dist-info/METADATA
nspektr-0.5.1.dist-info/WHEEL
nspektr-0.5.1.dist-info/top_level.txt
nspektr-0.5.1.dist-info/RECORD
